frontrunner_python_sdk/__init__.py
frontrunner_python_sdk/api_client.py
frontrunner_python_sdk/configuration.py
frontrunner_python_sdk/exceptions.py
frontrunner_python_sdk/rest.py
frontrunner_python_sdk/schemas.py
frontrunner_python_sdk/apis/__init__.py
frontrunner_python_sdk/apis/path_to_api.py
frontrunner_python_sdk/apis/tag_to_api.py
frontrunner_python_sdk/apis/paths/__init__.py
frontrunner_python_sdk/apis/paths/abbreviated_people_.py
frontrunner_python_sdk/apis/paths/abbreviated_people_id_.py
frontrunner_python_sdk/apis/paths/abbreviated_users_.py
frontrunner_python_sdk/apis/paths/abbreviated_users_id_.py
frontrunner_python_sdk/apis/paths/api_token_.py
frontrunner_python_sdk/apis/paths/feed_.py
frontrunner_python_sdk/apis/paths/feed_id_.py
frontrunner_python_sdk/apis/paths/integration_settings_facebook_.py
frontrunner_python_sdk/apis/paths/integration_settings_facebook_id_.py
frontrunner_python_sdk/apis/paths/integration_settings_mailchimp_.py
frontrunner_python_sdk/apis/paths/integration_settings_mailchimp_id_.py
frontrunner_python_sdk/apis/paths/integration_settings_prompt_.py
frontrunner_python_sdk/apis/paths/integration_settings_prompt_id_.py
frontrunner_python_sdk/apis/paths/integration_settings_revv_.py
frontrunner_python_sdk/apis/paths/integration_settings_revv_id_.py
frontrunner_python_sdk/apis/paths/integration_settings_twitter_.py
frontrunner_python_sdk/apis/paths/integration_settings_twitter_id_.py
frontrunner_python_sdk/apis/paths/integration_settings_whatsapp_.py
frontrunner_python_sdk/apis/paths/integration_settings_whatsapp_id_.py
frontrunner_python_sdk/apis/paths/integrations_all_.py
frontrunner_python_sdk/apis/paths/integrations_all_id_.py
frontrunner_python_sdk/apis/paths/integrations_mailchimp_.py
frontrunner_python_sdk/apis/paths/integrations_mailchimp_id_.py
frontrunner_python_sdk/apis/paths/integrations_prompt_.py
frontrunner_python_sdk/apis/paths/integrations_prompt_id_.py
frontrunner_python_sdk-0.0.8.dist-info/METADATA
frontrunner_python_sdk-0.0.8.dist-info/WHEEL
frontrunner_python_sdk-0.0.8.dist-info/top_level.txt
frontrunner_python_sdk-0.0.8.dist-info/RECORD
