Metadata-Version: 2.1
Name: frontrunner-python-sdk
Version: 0.0.8
Summary: FrontRunner API
Home-page: 
Author: OpenAPI Generator community
Author-email: team@openapitools.org
Project-URL: Homepage, https://github.com/frontrunnerapp/frontrunner-python-sdk
Keywords: OpenAPI,OpenAPI-Generator,FrontRunner API
Classifier: Programming Language :: Python :: 3
Classifier: License :: OSI Approved :: MIT License
Classifier: Operating System :: OS Independent
Requires-Python: >=3.7
Requires-Dist: urllib3 (>=1.15)
Requires-Dist: certifi
Requires-Dist: python-dateutil
Requires-Dist: frozendict (>=2.0.3)
Requires-Dist: typing-extensions
